warp/__init__.py
warp/__init__.pyi
warp/autograd.py
warp/build.py
warp/build_dll.py
warp/builtins.py
warp/codegen.py
warp/config.py
warp/constants.py
warp/context.py
warp/dlpack.py
warp/fabric.py
warp/jax.py
warp/math.py
warp/paddle.py
warp/sparse.py
warp/stubs.py
warp/tape.py
warp/torch.py
warp/types.py
warp/utils.py
warp/bin/warp-clang.so
warp/bin/warp.so
warp/examples/__init__.py
warp/examples/browse.py
warp/examples/assets/bear.usd
warp/examples/assets/bunny.usd
warp/examples/assets/cartpole.urdf
warp/examples/assets/crazyflie.usd
warp/examples/assets/cube.usd
warp/examples/assets/nonuniform.usd
warp/examples/assets/nv_ant.xml
warp/examples/assets/nv_humanoid.xml
warp/examples/assets/nvidia_logo.png
warp/examples/assets/pixel.jpg
warp/examples/assets/quadruped.urdf
warp/examples/assets/rocks.nvdb
warp/examples/assets/rocks.usd
warp/examples/assets/sphere.usd
warp/examples/assets/square_cloth.usd
warp/examples/benchmarks/benchmark_api.py
warp/examples/benchmarks/benchmark_cloth.py
warp/examples/benchmarks/benchmark_cloth_cupy.py
warp/examples/benchmarks/benchmark_cloth_jax.py
warp/examples/benchmarks/benchmark_cloth_numba.py
warp/examples/benchmarks/benchmark_cloth_numpy.py
warp/examples/benchmarks/benchmark_cloth_paddle.py
warp/examples/benchmarks/benchmark_cloth_pytorch.py
warp/examples/benchmarks/benchmark_cloth_taichi.py
warp/examples/benchmarks/benchmark_cloth_warp.py
warp/examples/benchmarks/benchmark_gemm.py
warp/examples/benchmarks/benchmark_interop_paddle.py
warp/examples/benchmarks/benchmark_interop_torch.py
warp/examples/benchmarks/benchmark_launches.py
warp/examples/benchmarks/benchmark_tile_load_store.py
warp/examples/core/example_cupy.py
warp/examples/core/example_dem.py
warp/examples/core/example_fluid.py
warp/examples/core/example_graph_capture.py
warp/examples/core/example_marching_cubes.py
warp/examples/core/example_mesh.py
warp/examples/core/example_mesh_intersect.py
warp/examples/core/example_nvdb.py
warp/examples/core/example_raycast.py
warp_lang-1.7.2.dist-info/licenses/LICENSE.md
warp_lang-1.7.2.dist-info/METADATA
warp_lang-1.7.2.dist-info/WHEEL
warp_lang-1.7.2.dist-info/top_level.txt
warp_lang-1.7.2.dist-info/RECORD
