Metadata-Version: 2.4
Name: warp-lang
Version: 1.7.2
Summary: A Python framework for high-performance simulation and graphics programming
Author-email: NVIDIA Corporation <warp-python@nvidia.com>
License: Apache-2.0
Project-URL: Homepage, https://developer.nvidia.com/warp-python
Project-URL: Documentation, https://nvidia.github.io/warp
Project-URL: Repository, https://github.com/NVIDIA/warp
Project-URL: Issues, https://github.com/NVIDIA/warp/issues
Project-URL: Changelog, https://github.com/NVIDIA/warp/blob/main/CHANGELOG.md
Classifier: Development Status :: 5 - Production/Stable
Classifier: Intended Audience :: Developers
Classifier: Intended Audience :: Science/Research
Classifier: Natural Language :: English
Classifier: Programming Language :: Python :: 3.8
Classifier: Programming Language :: Python :: 3.9
Classifier: Programming Language :: Python :: 3.10
Classifier: Programming Language :: Python :: 3.11
Classifier: Programming Language :: Python :: 3.12
Classifier: Programming Language :: Python :: 3.13
Classifier: Programming Language :: Python :: 3 :: Only
Classifier: Environment :: GPU :: NVIDIA CUDA
Classifier: Environment :: GPU :: NVIDIA CUDA :: 12
Classifier: Operating System :: OS Independent
Classifier: Topic :: Scientific/Engineering
Requires-Python: >=3.8
License-File: LICENSE.md
Requires-Dist: numpy
Provides-Extra: docs
Requires-Dist: nvidia-sphinx-theme; python_version >= "3.9" and extra == "docs"
Requires-Dist: sphinx-copybutton; extra == "docs"
Requires-Dist: ruff==0.11.10; extra == "docs"
Requires-Dist: myst_parser; extra == "docs"
Provides-Extra: dev
Requires-Dist: pre-commit; extra == "dev"
Requires-Dist: ruff==0.11.10; extra == "dev"
Requires-Dist: nvtx; extra == "dev"
Requires-Dist: nvidia-sphinx-theme; python_version >= "3.9" and extra == "dev"
Requires-Dist: sphinx-copybutton; extra == "dev"
Requires-Dist: coverage[toml]; extra == "dev"
Provides-Extra: extras
Requires-Dist: usd-core; extra == "extras"
Requires-Dist: matplotlib; extra == "extras"
Requires-Dist: pillow; extra == "extras"
Requires-Dist: pyglet; extra == "extras"
Dynamic: license-file
